mewicli/__init__.py
mewicli/cli.py
mewicli/main.py
mewicli/py.typed
mewicli-0.1.1.dist-info/LICENSE
mewicli-0.1.1.dist-info/LICENSE.apache2
mewicli-0.1.1.dist-info/LICENSE.mit
mewicli-0.1.1.dist-info/METADATA
mewicli-0.1.1.dist-info/WHEEL
mewicli-0.1.1.dist-info/entry_points.txt
mewicli-0.1.1.dist-info/RECORD
